labels/__init__.py
labels/advisories/__init__.py
labels/advisories/images/__init__.py
labels/advisories/images/database.py
labels/advisories/images/namespace.py
labels/advisories/images/version.py
labels/advisories/roots/__init__.py
labels/artifact/__init__.py
labels/artifact/relationship.py
labels/config/__init__.py
labels/config/bugsnag.py
labels/config/logger.py
labels/context/__init__.py
labels/core/__init__.py
labels/core/cli.py
labels/core/options.py
labels/core/sbom_configurator.py
labels/core/source_dispatcher.py
labels/file/__init__.py
labels/file/coordinates.py
labels/file/dependency_type.py
labels/file/location.py
labels/file/location_read_closer.py
labels/file/metadata.py
labels/file/resolver.py
labels/file/scope.py
labels/file/type.py
labels/format/__init__.py
labels/format/common.py
labels/format/cyclone_dx/__init__.py
labels/format/cyclone_dx/complete_file.py
labels/format/cyclone_dx/file_builder.py
labels/format/cyclone_dx/output_handler.py
labels/format/fluid.py
labels/format/spdx/__init__.py
labels/format/spdx/complete_file.py
labels/format/spdx/file_builder.py
labels/format/types.py
labels/internal/__init__.py
labels/internal/cache.py
labels/internal/collection/__init__.py
labels/internal/collection/json.py
labels/internal/collection/toml.py
labels/internal/collection/types.py
labels/internal/collection/yaml.py
labels/internal/digest.py
labels/internal/file/__init__.py
labels/internal/file/zip_file_manifest.py
labels/internal/file/zip_file_traversal.py
labels/internal/file_resolver/__init__.py
labels/internal/file_resolver/container_image.py
labels/internal/licenses/__init__.py
labels/internal/package_information/__init__.py
labels/internal/package_information/alpine.py
labels/internal/package_information/api_interface.py
labels/internal/package_information/dart.py
labels/internal/package_information/debian.py
labels/internal/package_information/dotnet.py
labels/internal/package_information/elixir.py
labels/internal/package_information/go.py
fluid_sbom-1.1.27.dist-info/METADATA
fluid_sbom-1.1.27.dist-info/WHEEL
fluid_sbom-1.1.27.dist-info/RECORD
