Metadata-Version: 2.1
Name: fluid-sbom
Version: 1.1.27
Summary: Fluid Attacks SBOM Library
License: MPL-2.0
Author: Development
Author-email: development@fluidattacks.com
Requires-Python: >=3.11,<4.0
Classifier: Development Status :: 3 - Alpha
Classifier: Intended Audience :: Developers
Classifier: License :: OSI Approved
Classifier: License :: OSI Approved :: Mozilla Public License 2.0 (MPL 2.0)
Classifier: Programming Language :: Python :: 3
Classifier: Programming Language :: Python :: 3.11
Classifier: Programming Language :: Python :: 3.12
Classifier: Programming Language :: Python :: 3.13
Classifier: Topic :: Software Development :: Libraries
Requires-Dist: aioboto3 (==13.0.1)
Requires-Dist: beautifulsoup4 (==4.12.3)
Requires-Dist: boto3 (==1.34.106)
Requires-Dist: bugsnag (==4.7.1)
Requires-Dist: click (==8.1.7)
Requires-Dist: confuse (==2.0.1)
Requires-Dist: cpe (==1.3.0)
Requires-Dist: cyclonedx-python-lib[json-validation,validation,xml-validation] (==8.1.0)
Requires-Dist: diskcache (==5.6.3)
Requires-Dist: furl (==2.1.3)
Requires-Dist: gemfileparser (==0.8.0)
Requires-Dist: more-itertools (==10.6.0)
Requires-Dist: os-release (==1.0.1)
Requires-Dist: pefile (==2023.2.7)
Requires-Dist: phpserialize (==1.3)
Requires-Dist: platformdirs (==4.3.6)
Requires-Dist: pydantic (==2.10.5)
Requires-Dist: reactivex (==4.0.4)
Requires-Dist: redis (==5.0.7)
Requires-Dist: requests (==2.32.3)
Requires-Dist: requirements-parser (==0.11.0)
Requires-Dist: retry-requests (==2.0.0)
Requires-Dist: spdx-lookup (==0.3.3)
Requires-Dist: spdx-matcher (==0.1.1)
Requires-Dist: spdx-tools (==0.8.2)
Requires-Dist: tqdm (==4.66.5)
Requires-Dist: tree-sitter (==0.24.0)
Requires-Dist: tree-sitter-json (==0.24.8)
Requires-Dist: tree-sitter-toml (==0.7.0)
Requires-Dist: tree-sitter-yaml (==0.7.0)
Requires-Dist: univers (==30.12.1)
